CHANGES.rst
CONTRIBUTORS.rst
MANIFEST.in
README.rst
setup.cfg
setup.py
collective/__init__.py
collective.ogtags.egg-info/PKG-INFO
collective.ogtags.egg-info/SOURCES.txt
collective.ogtags.egg-info/dependency_links.txt
collective.ogtags.egg-info/entry_points.txt
collective.ogtags.egg-info/namespace_packages.txt
collective.ogtags.egg-info/not-zip-safe
collective.ogtags.egg-info/requires.txt
collective.ogtags.egg-info/top_level.txt
collective/ogtags/__init__.py
collective/ogtags/adapters.py
collective/ogtags/configure.zcml
collective/ogtags/i18ndude.sh
collective/ogtags/interfaces.py
collective/ogtags/browser/__init__.py
collective/ogtags/browser/configure.zcml
collective/ogtags/browser/controlpanel.py
collective/ogtags/browser/ogtags_head.pt
collective/ogtags/browser/permissions.zcml
collective/ogtags/browser/viewlets.py
collective/ogtags/locales/collective.ogtags.pot
collective/ogtags/locales/nl/LC_MESSAGES/collective.ogtags.po
collective/ogtags/profiles/default/controlpanel.xml
collective/ogtags/profiles/default/metadata.xml
collective/ogtags/profiles/default/registry.xml
collective/ogtags/profiles/uninstall/controlpanel.xml
collective/ogtags/profiles/uninstall/registry.xml
docs/INSTALL.txt
docs/LICENSE.GPL
docs/LICENSE.txt