Metadata-Version: 1.1
Name: collective.ogtags
Version: 2.0.2
Summary: OpenGraph for plone5
Home-page: https://zestsoftware.nl/
Author: Diederik Veeze
Author-email: d.veeze@zestsoftware.nl
License: GPL
Keywords: OpenGraph tags facebook twitter linkedin
Platform: UNKNOWN
Classifier: Framework :: Plone
Classifier: Programming Language :: Python
Classifier: Framework :: Plone :: 5.1
Classifier: Programming Language :: Python :: 2.7
